setup.py
blueberrymath/Calculus.py
blueberrymath/Matrix.py
blueberrymath/Sample.py
blueberrymath/Stats.py
blueberrymath/Vect.py
blueberrymath/VectorCoords.py
blueberrymath/__init__.py
blueberrymath.egg-info/PKG-INFO
blueberrymath.egg-info/SOURCES.txt
blueberrymath.egg-info/dependency_links.txt
blueberrymath.egg-info/requires.txt
blueberrymath.egg-info/top_level.txt