Metadata-Version: 1.1
Name: blueberrymath
Version: 0.1.1
Summary: Open Source Mathematical Package
Home-page: https://github.com/faustotnc/BlueBerryMath
Author: Fausto German
Author-email: faustotnc@gmail.com
License: MIT
Platform: UNKNOWN
Classifier: Development Status :: 1 - Planning
Classifier: Intended Audience :: Science/Research
Classifier: License :: OSI Approved :: MIT License
Classifier: Operating System :: POSIX :: Linux
Classifier: Programming Language :: Python :: 2
Classifier: Programming Language :: Python :: 2.7
Classifier: Programming Language :: Python :: 3
Classifier: Programming Language :: Python :: 3.4
Classifier: Programming Language :: Python :: 3.5
